<?xml version="1.0" encoding="utf-8" ?>
<c2uistate>
    <!--This is a UI state file - its content describes the user interface settings when the project was last open.
It is entirely optional and the project will load without it.  If you are placing the project under source control,
you probably do not want to add any .uistate.xml files to the repository.-->
    <configurations>
        <active>
            <configuration name="HTML5" />
        </active>
        <display name="HTML5" />
    </configurations>
    <open-tabs>
        <layout order="0">Game</layout>
        <layout active="1" order="1">Launcher</layout>
        <event-sheet order="2">Game Event sheet</event-sheet>
        <event-sheet order="3">Launcher Event sheet</event-sheet>
    </open-tabs>
    <properties>
        <property expanded="1" name="About" />
        <property expanded="1" name="Project settings" />
        <property expanded="1" name="Window Size" />
        <property expanded="1" name="Configuration Settings" />
    </properties>
    <families-expanded root="1" />
    <folders-expanded>
        <folder expanded="1" path="object-folder/" />
        <folder expanded="1" path="object-folder/DialogBox/" />
        <folder expanded="0" path="object-folder/SailingInterface/" />
        <folder expanded="0" path="object-folder/1-Launcher/" />
        <folder expanded="1" path="object-folder/Shop/" />
        <folder expanded="0" path="object-folder/Police patroles/" />
        <folder expanded="0" path="object-folder/0-Utils/" />
        <folder expanded="0" path="object-folder/Geo/" />
        <folder expanded="1" path="layout-folder/" />
        <folder expanded="1" path="event-folder/" />
        <folder expanded="0" path="file-folder/" />
        <folder expanded="0" path="sound-folder/" />
        <folder expanded="0" path="music-folder/" />
        <folder expanded="0" path="file-folder/Icons/" />
        <folder expanded="1" path="animation-folder/DBDialogBox/" />
        <folder expanded="1" path="animation-folder/DBImgHero/" />
        <folder expanded="1" path="animation-folder/DBImgInterlocutor/" />
        <folder expanded="1" path="animation-folder/SIActionBox/" />
        <folder expanded="1" path="animation-folder/SIChallengeBarMulti/" />
        <folder expanded="1" path="animation-folder/SIChallengeLeftBounce/" />
        <folder expanded="1" path="animation-folder/SIChallengePlayBall/" />
        <folder expanded="1" path="animation-folder/SIChallengeRightBounce/" />
        <folder expanded="1" path="animation-folder/SIChallengeWinArea/" />
        <folder expanded="1" path="animation-folder/SIIconFish/" />
        <folder expanded="1" path="animation-folder/SIIconNews/" />
        <folder expanded="1" path="animation-folder/SIAnchor/" />
        <folder expanded="1" path="animation-folder/SILeftBackground/" />
        <folder expanded="1" path="animation-folder/laucherBackground/" />
        <folder expanded="1" path="animation-folder/launcherImg2/" />
        <folder expanded="1" path="animation-folder/launcherImg1/" />
        <folder expanded="1" path="animation-folder/shopBox/" />
        <folder expanded="1" path="animation-folder/shopSeller/" />
        <folder expanded="1" path="animation-folder/policeBoat1PatroleTop/" />
        <folder expanded="1" path="animation-folder/policeBoat1/" />
        <folder expanded="1" path="animation-folder/policeBoat1PatroleBottom/" />
        <folder expanded="1" path="animation-folder/limit1to2/" />
        <folder expanded="1" path="animation-folder/limit2to3/" />
        <folder expanded="1" path="animation-folder/limitGoltin/" />
        <folder expanded="1" path="animation-folder/limitTungo/" />
        <folder expanded="1" path="animation-folder/cityEwuh/" />
        <folder expanded="1" path="animation-folder/cityGoltinTantalene/" />
        <folder expanded="1" path="animation-folder/cityTungoNastassia/" />
        <folder expanded="1" path="animation-folder/cityTungoPraskovia/" />
        <folder expanded="1" path="animation-folder/boat/" />
        <folder expanded="1" path="animation-folder/wind/" />
        <folder expanded="1" path="animation-folder/homeTungo/" />
        <folder expanded="1" path="animation-folder/fishingArea/" />
        <folder expanded="1" path="animation-folder/night/" />
        <folder expanded="1" path="animation-folder/shopTungo/" />
        <folder expanded="1" path="animation-folder/SIAnemometre/" />
        <folder expanded="1" path="animation-folder/Sprite/" />
        <folder expanded="1" path="animation-folder/Sprite2/" />
    </folders-expanded>
</c2uistate>
